function_comment/__init__.py
function_comment/decorators.py
tests/__init__.py
tests/test_decorators.py
function_comment-0.1.0.dist-info/LICENSE
function_comment-0.1.0.dist-info/METADATA
function_comment-0.1.0.dist-info/WHEEL
function_comment-0.1.0.dist-info/top_level.txt
function_comment-0.1.0.dist-info/RECORD
